scape/__init__.py
scape/__main__.py
scape/apa_core.py
scape/cli.py
scape/input_processor.py
scape/junction_handler.py
scape/taichi_code_test.py
scape/taichi_core.py
scape/utils.py
scape_apa-1.0.4.dist-info/LICENSE
scape_apa-1.0.4.dist-info/METADATA
scape_apa-1.0.4.dist-info/WHEEL
scape_apa-1.0.4.dist-info/entry_points.txt
scape_apa-1.0.4.dist-info/top_level.txt
scape_apa-1.0.4.dist-info/RECORD
